LICENSE.txt
README.md
pyreqify/__init__.py
pyreqify/extractor.py
pyreqify-0.0.11.dist-info/METADATA
pyreqify-0.0.11.dist-info/WHEEL
pyreqify-0.0.11.dist-info/entry_points.txt
pyreqify-0.0.11.dist-info/licenses/LICENSE.txt
pyreqify-0.0.11.dist-info/RECORD
