Metadata-Version: 2.4
Name: pyreqify
Version: 0.0.11
Summary: A module to extract Python dependencies packages from .py and .ipynb
Project-URL: Homepage, https://github.com/ammaryasirnaich/PyReqify
Project-URL: Documentation, https://github.com/ammaryasirnaich/PyReqify
Project-URL: Source Code, https://github.com/ammaryasirnaich/PyReqify
Author-email: Ammar Yasir Naich <ammar.naich@gmail.com>
License: MIT License
License-File: LICENSE.txt
Keywords: Python modules,automation,dependency management,requirements,requirements.txt
Classifier: Intended Audience :: Developers
Classifier: License :: OSI Approved :: MIT License
Classifier: Operating System :: OS Independent
Classifier: Programming Language :: Python :: 3
Classifier: Topic :: Software Development :: Libraries :: Python Modules
Requires-Python: >=3.8
Requires-Dist: nbformat
